aws_pcluster_helpers/__init__.py
aws_pcluster_helpers/_version.py
aws_pcluster_helpers/cli.py
aws_pcluster_helpers/commands/__init__.py
aws_pcluster_helpers/commands/cli_gen_nxf_slurm_config.py
aws_pcluster_helpers/commands/cli_sinfo.py
aws_pcluster_helpers/models/__init__.py
aws_pcluster_helpers/models/config.py
aws_pcluster_helpers/models/instance_types_data.py
aws_pcluster_helpers/models/nextflow.py
aws_pcluster_helpers/models/pcluster_config.py
aws_pcluster_helpers/models/sinfo.py
aws_pcluster_helpers/models/_templates/slurm.config
aws_pcluster_helpers/utils/__init__.py
aws_pcluster_helpers/utils/logging.py
aws_pcluster_helpers-2023.9.26.data/data/templates/slurm.config
aws_pcluster_helpers-2023.9.26.dist-info/LICENSE
aws_pcluster_helpers-2023.9.26.dist-info/METADATA
aws_pcluster_helpers-2023.9.26.dist-info/WHEEL
aws_pcluster_helpers-2023.9.26.dist-info/entry_points.txt
aws_pcluster_helpers-2023.9.26.dist-info/top_level.txt
aws_pcluster_helpers-2023.9.26.dist-info/RECORD
