Metadata-Version: 2.1
Name: aws-pcluster-helpers
Version: 2023.9.26
Summary: Helpers to generate different configurations for PCluster
Home-page: https://github.com/dabble-of-devops-bioanalyze/aws_pcluster_helpers
Author: Jillian Rowe
Author-email: jillian@dabbleofdevops.com
License: Apache Software License 2.0
Keywords: aws_pcluster_helpers
Classifier: Development Status :: 2 - Pre-Alpha
Classifier: Intended Audience :: Developers
Classifier: License :: OSI Approved :: Apache Software License
Classifier: Natural Language :: English
Classifier: Programming Language :: Python :: 3
Classifier: Programming Language :: Python :: 3.6
Classifier: Programming Language :: Python :: 3.7
Classifier: Programming Language :: Python :: 3.8
Requires-Python: >=3.6
License-File: LICENSE
Requires-Dist: devtools
Requires-Dist: colorlog
Requires-Dist: boto3
Requires-Dist: boto3-stubs[essential]
Requires-Dist: datasize
Requires-Dist: humanize
Requires-Dist: rich-click
Requires-Dist: pandas
Requires-Dist: cookiecutter
Requires-Dist: aws-parallelcluster >=3.5
Requires-Dist: typer
Requires-Dist: pydantic >=2.3
